{"objects":[{"type":"image","version":"4.6.0","originX":"left","originY":"top","left":148,"top":109.8,"width":600,"height":400,"fill":"rgb(0,0,0)","stroke":null,"strokeWidth":0,"strokeDashArray":null,"strokeLineCap":"butt","strokeDashOffset":0,"strokeLineJoin":"miter","strokeUniform":false,"strokeMiterLimit":4,"scaleX":1,"scaleY":1,"angle":0,"flipX":false,"flipY":false,"opacity":1,"shadow":null,"visible":true,"backgroundColor":"#fff","fillRule":"nonzero","paintFirst":"fill","globalCompositeOperation":"source-over","skewX":0,"skewY":0,"cropX":0,"cropY":0,"id":"workarea","name":"","link":{},"tooltip":{"enabled":false},"layout":"fixed","workareaWidth":600,"workareaHeight":400,"src":"","crossOrigin":null,"filters":[]},{"type":"circle","version":"4.6.0","originX":"left","originY":"top","left":286.26,"top":235.05,"width":60,"height":60,"fill":"rgba(10,10,10,1)","stroke":"rgba(255, 255, 255, 0)","strokeWidth":1,"strokeDashArray":null,"strokeLineCap":"butt","strokeDashOffset":0,"strokeLineJoin":"miter","strokeUniform":true,"strokeMiterLimit":4,"scaleX":2.04,"scaleY":2.04,"angle":0,"flipX":false,"flipY":false,"opacity":1,"shadow":null,"visible":true,"backgroundColor":"","fillRule":"nonzero","paintFirst":"fill","globalCompositeOperation":"source-over","skewX":0,"skewY":0,"radius":30,"startAngle":0,"endAngle":6.283185307179586,"id":"d50d7213-6c77-4e78-9a0b-bb406ec5f693","name":"New shape","link":{"enabled":false,"type":"resource","state":"new","dashboard":{}},"tooltip":{"enabled":true,"type":"resource","template":"<div>{{message.name}}</div>"},"animation":{"type":"none","loop":true,"autoplay":true,"duration":1000},"userProperty":{},"trigger":{"enabled":false,"type":"alarm","script":"return message.value > 0;","effect":"style"},"editable":true},{"type":"circle","version":"4.6.0","originX":"left","originY":"top","left":336.48,"top":259.32,"width":60,"height":60,"fill":"rgba(250,250,250,1)","stroke":"rgba(255, 255, 255, 0)","strokeWidth":1,"strokeDashArray":null,"strokeLineCap":"butt","strokeDashOffset":0,"strokeLineJoin":"miter","strokeUniform":true,"strokeMiterLimit":4,"scaleX":0.78,"scaleY":0.78,"angle":0,"flipX":false,"flipY":false,"opacity":1,"shadow":null,"visible":true,"backgroundColor":"","fillRule":"nonzero","paintFirst":"fill","globalCompositeOperation":"source-over","skewX":0,"skewY":0,"radius":30,"startAngle":0,"endAngle":6.283185307179586,"id":"df44f5aa-86b0-4f71-ad0e-18da65523ec8","name":"New shape","link":{"enabled":false,"type":"resource","state":"new","dashboard":{}},"tooltip":{"enabled":true,"type":"resource","template":"<div>{{message.name}}</div>"},"animation":{"type":"none","loop":true,"autoplay":true,"duration":1000},"userProperty":{},"trigger":{"enabled":false,"type":"alarm","script":"return message.value > 0;","effect":"style"},"editable":true},{"type":"circle","version":"4.6.0","originX":"left","originY":"top","left":347.98,"top":272.3,"width":60,"height":60,"fill":"rgba(195,195,195,1)","stroke":"rgba(255, 255, 255, 0)","strokeWidth":1,"strokeDashArray":null,"strokeLineCap":"butt","strokeDashOffset":0,"strokeLineJoin":"miter","strokeUniform":true,"strokeMiterLimit":4,"scaleX":0.35,"scaleY":0.35,"angle":0,"flipX":false,"flipY":false,"opacity":1,"shadow":null,"visible":true,"backgroundColor":"","fillRule":"nonzero","paintFirst":"fill","globalCompositeOperation":"source-over","skewX":0,"skewY":0,"radius":30,"startAngle":0,"endAngle":6.283185307179586,"id":"d337a183-99cc-429c-87e7-202cec94db96","name":"New shape","link":{"enabled":false,"type":"resource","state":"new","dashboard":{}},"tooltip":{"enabled":true,"type":"resource","template":"<div>{{message.name}}</div>"},"animation":{"type":"none","loop":true,"autoplay":true,"duration":1000},"userProperty":{},"trigger":{"enabled":false,"type":"alarm","script":"return message.value > 0;","effect":"style"},"editable":true},{"type":"circle","version":"4.6.0","originX":"left","originY":"top","left":459.3,"top":235.1,"width":60,"height":60,"fill":"rgba(10,10,10,1)","stroke":"rgba(255, 255, 255, 0)","strokeWidth":1,"strokeDashArray":null,"strokeLineCap":"butt","strokeDashOffset":0,"strokeLineJoin":"miter","strokeUniform":true,"strokeMiterLimit":4,"scaleX":2.04,"scaleY":2.04,"angle":0,"flipX":false,"flipY":false,"opacity":1,"shadow":null,"visible":true,"backgroundColor":"","fillRule":"nonzero","paintFirst":"fill","globalCompositeOperation":"source-over","skewX":0,"skewY":0,"radius":30,"startAngle":0,"endAngle":6.283185307179586,"id":"a66d67ea-a067-4f2a-b715-24d79b1a434d","name":"New shape","link":{"enabled":false,"type":"resource","state":"new","dashboard":{}},"tooltip":{"enabled":true,"type":"resource","template":"<div>{{message.name}}</div>"},"animation":{"type":"none","loop":true,"autoplay":true,"duration":1000},"userProperty":{},"trigger":{"enabled":false,"type":"alarm","script":"return message.value > 0;","effect":"style"},"editable":true},{"type":"circle","version":"4.6.0","originX":"left","originY":"top","left":479.52,"top":259.54,"width":60,"height":60,"fill":"rgba(250,250,250,1)","stroke":"rgba(255, 255, 255, 0)","strokeWidth":1,"strokeDashArray":null,"strokeLineCap":"butt","strokeDashOffset":0,"strokeLineJoin":"miter","strokeUniform":true,"strokeMiterLimit":4,"scaleX":0.78,"scaleY":0.78,"angle":0,"flipX":false,"flipY":false,"opacity":1,"shadow":null,"visible":true,"backgroundColor":"","fillRule":"nonzero","paintFirst":"fill","globalCompositeOperation":"source-over","skewX":0,"skewY":0,"radius":30,"startAngle":0,"endAngle":6.283185307179586,"id":"93b2f24e-faf2-41fa-978b-5ada41f1a8ee","name":"New shape","link":{"enabled":false,"type":"resource","state":"new","dashboard":{}},"tooltip":{"enabled":true,"type":"resource","template":"<div>{{message.name}}</div>"},"animation":{"type":"none","loop":true,"autoplay":true,"duration":1000},"userProperty":{},"trigger":{"enabled":false,"type":"alarm","script":"return message.value > 0;","effect":"style"},"editable":true},{"type":"circle","version":"4.6.0","originX":"left","originY":"top","left":486.02,"top":267.35,"width":60,"height":60,"fill":"rgba(195,195,195,1)","stroke":"rgba(255, 255, 255, 0)","strokeWidth":1,"strokeDashArray":null,"strokeLineCap":"butt","strokeDashOffset":0,"strokeLineJoin":"miter","strokeUniform":true,"strokeMiterLimit":4,"scaleX":0.35,"scaleY":0.35,"angle":0,"flipX":false,"flipY":false,"opacity":1,"shadow":null,"visible":true,"backgroundColor":"","fillRule":"nonzero","paintFirst":"fill","globalCompositeOperation":"source-over","skewX":0,"skewY":0,"radius":30,"startAngle":0,"endAngle":6.283185307179586,"id":"542f3416-b013-4a2a-9608-83d30c73e7ee","name":"New shape","link":{"enabled":false,"type":"resource","state":"new","dashboard":{}},"tooltip":{"enabled":true,"type":"resource","template":"<div>{{message.name}}</div>"},"animation":{"type":"none","loop":true,"autoplay":true,"duration":1000},"userProperty":{},"trigger":{"enabled":false,"type":"alarm","script":"return message.value > 0;","effect":"style"},"editable":true}],"animations":[],"styles":[],"dataSources":[]}